Tool.py
yyc_package/__init__.py
yyc_package/yyc_module.py
yyc_package_test-1.0.0.dist-info/LICENSE.txt
yyc_package_test-1.0.0.dist-info/METADATA
yyc_package_test-1.0.0.dist-info/WHEEL
yyc_package_test-1.0.0.dist-info/top_level.txt
yyc_package_test-1.0.0.dist-info/RECORD
