Metadata-Version: 2.1
Name: yyc_package_test
Version: 1.0.0
Summary: this is yyc's first package
Author: yyc
License-File: LICENSE.txt
